{"version": 2, "backend": "simple", "variable_types": {}, "scalar": {"power2": 0, "phase": "0"}, "inputs": [], "outputs": [], "edata": {}, "vertices": [{"id": 64, "t": 1, "pos": [2.0, 8.0]}, {"id": 39, "t": 1, "pos": [1.0, 8.0]}, {"id": 65, "t": 2, "pos": [2.0, 1]}, {"id": 67, "t": 2, "pos": [3.0, 8.0]}, {"id": 66, "t": 1, "pos": [3.0, 18.0]}, {"id": 79, "t": 2, "pos": [9.0, 8.0]}, {"id": 78, "t": 1, "pos": [9.0, 14.0]}, {"id": 85, "t": 2, "pos": [12.0, 8.0]}, {"id": 84, "t": 1, "pos": [12.0, 27.0]}, {"id": 114, "t": 1, "pos": [27.0, 8.0]}, {"id": 115, "t": 2, "pos": [27.0, 31.0]}, {"id": 135, "t": 1, "pos": [35.0, 8.0]}, {"id": 58, "t": 1, "pos": [1.0, 27.0]}, {"id": 89, "t": 2, "pos": [14.0, 27.0]}, {"id": 206, "t": 1, "pos": [13.0, 27.0]}, {"id": 88, "t": 1, "pos": [14.0, 18.0]}, {"id": 109, "t": 2, "pos": [24.0, 27.0]}, {"id": 108, "t": 1, "pos": [24.0, 17.0]}, {"id": 154, "t": 1, "pos": [35.0, 27.0]}, {"id": 48, "t": 1, "pos": [1.0, 17.0]}, {"id": 144, "t": 1, "pos": [35.0, 17.0]}, {"id": 176, "t": 0, "pos": [36.0, 17.0]}, {"id": 49, "t": 1, "pos": [1.0, 18.0]}, {"id": 215, "t": 2, "pos": [10.333, 18.0]}, {"id": 216, "t": 2, "pos": [6.667, 18.0]}, {"id": 96, "t": 1, "pos": [18.0, 18.0]}, {"id": 97, "t": 2, "pos": [18.0, 5.0]}, {"id": 113, "t": 2, "pos": [26.0, 18.0]}, {"id": 112, "t": 1, "pos": [26.0, 30.0]}, {"id": 145, "t": 1, "pos": [35.0, 18.0]}, {"id": 45, "t": 1, "pos": [1.0, 14.0]}, {"id": 98, "t": 1, "pos": [19.0, 14.0]}, {"id": 99, "t": 2, "pos": [19.0, 32.0]}, {"id": 103, "t": 2, "pos": [21.0, 14.0]}, {"id": 102, "t": 1, "pos": [21.0, 6.0]}, {"id": 227, "t": 1, "pos": [21.0, 10.0]}, {"id": 141, "t": 1, "pos": [35.0, 14.0]}, {"id": 173, "t": 0, "pos": [36.0, 14.0]}, {"id": 61, "t": 1, "pos": [1.0, 30.0]}, {"id": 157, "t": 1, "pos": [35.0, 30.0]}, {"id": 189, "t": 0, "pos": [36.0, 30.0]}, {"id": 63, "t": 1, "pos": [1.0, 32.0]}, {"id": 31, "t": 0, "pos": [0.0, 32.0]}, {"id": 159, "t": 1, "pos": [35.0, 32.0]}, {"id": 62, "t": 1, "pos": [1.0, 31.0]}, {"id": 158, "t": 1, "pos": [35.0, 31.0]}, {"id": 190, "t": 0, "pos": [36.0, 31.0]}, {"id": 72, "t": 1, "pos": [6.0, 6.0]}, {"id": 133, "t": 1, "pos": [35.0, 6.0]}, {"id": 241, "t": 1, "pos": [28.0, 6.0]}, {"id": 165, "t": 0, "pos": [36.0, 6.0]}, {"id": 69, "t": 2, "pos": [4.0, 5.0]}, {"id": 36, "t": 1, "pos": [1.0, 5.0]}, {"id": 4, "t": 0, "pos": [0.0, 5.0]}, {"id": 68, "t": 1, "pos": [4.0, 15.0]}, {"id": 46, "t": 1, "pos": [1.0, 15.0]}, {"id": 14, "t": 0, "pos": [0.0, 15.0]}, {"id": 126, "t": 1, "pos": [34.0, 15.0]}, {"id": 127, "t": 2, "pos": [34.0, 26.0]}, {"id": 142, "t": 1, "pos": [35.0, 15.0]}, {"id": 174, "t": 0, "pos": [36.0, 15.0]}, {"id": 32, "t": 1, "pos": [1.0, 1]}, {"id": 90, "t": 1, "pos": [15.0, 1]}, {"id": 91, "t": 2, "pos": [15.0, 26.0]}, {"id": 128, "t": 1, "pos": [35.0, 1]}, {"id": 160, "t": 0, "pos": [36.0, 1]}, {"id": 57, "t": 1, "pos": [1.0, 26.0]}, {"id": 259, "t": 2, "pos": [32.812, 26.0]}, {"id": 260, "t": 2, "pos": [31.625, 26.0]}, {"id": 261, "t": 2, "pos": [30.438, 26.0]}, {"id": 262, "t": 2, "pos": [29.25, 26.0]}, {"id": 263, "t": 1, "pos": [28.062, 26.0]}, {"id": 264, "t": 2, "pos": [26.875, 26.0]}, {"id": 265, "t": 2, "pos": [25.688, 26.0]}, {"id": 266, "t": 2, "pos": [24.5, 26.0]}, {"id": 267, "t": 2, "pos": [23.312, 26.0]}, {"id": 268, "t": 2, "pos": [22.125, 26.0]}, {"id": 269, "t": 2, "pos": [20.938, 26.0]}, {"id": 270, "t": 2, "pos": [19.75, 26.0]}, {"id": 271, "t": 2, "pos": [18.562, 26.0]}, {"id": 272, "t": 2, "pos": [17.375, 26.0]}, {"id": 273, "t": 2, "pos": [16.188, 26.0]}, {"id": 153, "t": 1, "pos": [35.0, 26.0]}, {"id": 37, "t": 1, "pos": [1.0, 6.0]}, {"id": 5, "t": 0, "pos": [0.0, 6.0]}, {"id": 73, "t": 2, "pos": [6.0, 20.0]}, {"id": 51, "t": 1, "pos": [1.0, 20.0]}, {"id": 107, "t": 2, "pos": [23.0, 20.0]}, {"id": 106, "t": 1, "pos": [23.0, 23.0]}, {"id": 147, "t": 1, "pos": [35.0, 20.0]}, {"id": 71, "t": 2, "pos": [5.0, 23.0]}, {"id": 283, "t": 1, "pos": [14.0, 23.0]}, {"id": 150, "t": 1, "pos": [35.0, 23.0]}, {"id": 54, "t": 1, "pos": [1.0, 23.0]}, {"id": 70, "t": 1, "pos": [5.0, 7.0]}, {"id": 38, "t": 1, "pos": [1.0, 7.0]}, {"id": 104, "t": 1, "pos": [22.0, 7.0]}, {"id": 289, "t": 2, "pos": [16.333, 7.0]}, {"id": 290, "t": 1, "pos": [10.667, 7.0]}, {"id": 105, "t": 2, "pos": [22.0, 13.0]}, {"id": 134, "t": 1, "pos": [35.0, 7.0]}, {"id": 82, "t": 1, "pos": [11.0, 13.0]}, {"id": 122, "t": 1, "pos": [32.0, 13.0]}, {"id": 123, "t": 2, "pos": [32.0, 24.0]}, {"id": 140, "t": 1, "pos": [35.0, 13.0]}, {"id": 172, "t": 0, "pos": [36.0, 13.0]}, {"id": 120, "t": 1, "pos": [30.0, 24.0]}, {"id": 299, "t": 1, "pos": [31.0, 24.0]}, {"id": 151, "t": 1, "pos": [35.0, 24.0]}, {"id": 183, "t": 0, "pos": [36.0, 24.0]}, {"id": 93, "t": 2, "pos": [16.0, 24.0]}, {"id": 121, "t": 2, "pos": [30.0, 19.0]}, {"id": 118, "t": 1, "pos": [29.0, 19.0]}, {"id": 146, "t": 1, "pos": [35.0, 19.0]}, {"id": 83, "t": 2, "pos": [11.0, 24.0]}, {"id": 92, "t": 1, "pos": [16.0, 11.0]}, {"id": 42, "t": 1, "pos": [1.0, 11.0]}, {"id": 95, "t": 2, "pos": [17.0, 11.0]}, {"id": 94, "t": 1, "pos": [17.0, 28.0]}, {"id": 138, "t": 1, "pos": [35.0, 11.0]}, {"id": 170, "t": 0, "pos": [36.0, 11.0]}, {"id": 44, "t": 1, "pos": [1.0, 13.0]}, {"id": 12, "t": 0, "pos": [0.0, 13.0]}, {"id": 315, "t": 2, "pos": [11.0, 15.2]}, {"id": 316, "t": 2, "pos": [11.0, 17.4]}, {"id": 317, "t": 2, "pos": [11.0, 19.6]}, {"id": 318, "t": 2, "pos": [11.0, 21.8]}, {"id": 55, "t": 1, "pos": [1.0, 24.0]}, {"id": 87, "t": 2, "pos": [13.0, 19.0]}, {"id": 119, "t": 2, "pos": [29.0, 28.0]}, {"id": 322, "t": 1, "pos": [29.0, 23.5]}, {"id": 155, "t": 1, "pos": [35.0, 28.0]}, {"id": 187, "t": 0, "pos": [36.0, 28.0]}, {"id": 325, "t": 2, "pos": [27.0, 28.0]}, {"id": 326, "t": 2, "pos": [25.0, 28.0]}, {"id": 327, "t": 2, "pos": [23.0, 28.0]}, {"id": 328, "t": 1, "pos": [21.0, 28.0]}, {"id": 329, "t": 1, "pos": [19.0, 28.0]}, {"id": 74, "t": 1, "pos": [7.0, 28.0]}, {"id": 59, "t": 1, "pos": [1.0, 28.0]}, {"id": 27, "t": 0, "pos": [0.0, 28.0]}, {"id": 75, "t": 2, "pos": [7.0, 2.0]}, {"id": 81, "t": 2, "pos": [10.0, 19.0]}, {"id": 86, "t": 1, "pos": [13.0, 29.0]}, {"id": 336, "t": 1, "pos": [13.0, 24.0]}, {"id": 60, "t": 1, "pos": [1.0, 29.0]}, {"id": 28, "t": 0, "pos": [0.0, 29.0]}, {"id": 156, "t": 1, "pos": [35.0, 29.0]}, {"id": 188, "t": 0, "pos": [36.0, 29.0]}, {"id": 50, "t": 1, "pos": [1.0, 19.0]}, {"id": 18, "t": 0, "pos": [0.0, 19.0]}, {"id": 80, "t": 1, "pos": [10.0, 2.0]}, {"id": 29, "t": 0, "pos": [0.0, 30.0]}, {"id": 178, "t": 0, "pos": [36.0, 19.0]}, {"id": 185, "t": 0, "pos": [36.0, 26.0]}, {"id": 167, "t": 0, "pos": [36.0, 8.0]}, {"id": 166, "t": 0, "pos": [36.0, 7.0]}, {"id": 191, "t": 0, "pos": [36.0, 32.0]}, {"id": 182, "t": 0, "pos": [36.0, 23.0]}, {"id": 179, "t": 0, "pos": [36.0, 20.0]}, {"id": 26, "t": 0, "pos": [0.0, 27.0]}, {"id": 13, "t": 0, "pos": [0.0, 14.0]}, {"id": 186, "t": 0, "pos": [36.0, 27.0]}, {"id": 177, "t": 0, "pos": [36.0, 18.0]}, {"id": 16, "t": 0, "pos": [0.0, 17.0]}, {"id": 25, "t": 0, "pos": [0.0, 26.0]}, {"id": 30, "t": 0, "pos": [0.0, 31.0]}, {"id": 7, "t": 0, "pos": [0.0, 8.0]}, {"id": 6, "t": 0, "pos": [0.0, 7.0]}, {"id": 22, "t": 0, "pos": [0.0, 23.0]}, {"id": 19, "t": 0, "pos": [0.0, 20.0]}, {"id": 10, "t": 0, "pos": [0.0, 11.0]}, {"id": 17, "t": 0, "pos": [0.0, 18.0]}, {"id": 23, "t": 0, "pos": [0.0, 24.0]}, {"id": 0, "t": 0, "pos": [0.0, 1]}], "edges": [[64, 65, 1], [64, 67, 1], [39, 64, 1], [65, 90, 1], [67, 79, 1], [66, 67, 1], [66, 215, 1], [79, 85, 1], [78, 79, 1], [78, 98, 1], [85, 114, 1], [84, 85, 1], [84, 206, 1], [114, 115, 1], [114, 135, 1], [115, 158, 1], [135, 167, 1], [58, 84, 1], [89, 206, 1], [89, 109, 1], [88, 89, 1], [88, 216, 1], [88, 96, 1], [109, 154, 1], [108, 109, 1], [108, 144, 1], [154, 186, 1], [48, 108, 1], [144, 176, 1], [49, 66, 1], [215, 216, 1], [96, 97, 1], [96, 113, 1], [113, 145, 1], [112, 113, 1], [112, 157, 1], [145, 177, 1], [45, 78, 1], [98, 99, 1], [98, 103, 1], [99, 159, 1], [103, 227, 1], [103, 141, 1], [102, 227, 1], [102, 241, 1], [141, 173, 1], [61, 112, 1], [157, 189, 1], [63, 99, 1], [31, 63, 1], [159, 191, 1], [62, 115, 1], [158, 190, 1], [72, 102, 1], [72, 73, 1], [133, 241, 1], [133, 165, 1], [69, 97, 1], [36, 69, 1], [4, 36, 1], [68, 69, 1], [68, 126, 1], [46, 68, 1], [14, 46, 1], [126, 127, 1], [126, 142, 1], [127, 273, 1], [127, 153, 1], [142, 174, 1], [32, 65, 1], [90, 91, 1], [90, 128, 1], [91, 259, 1], [128, 160, 1], [57, 91, 1], [259, 260, 1], [260, 261, 1], [261, 262, 1], [262, 263, 1], [263, 264, 1], [264, 265, 1], [265, 266, 1], [266, 267, 1], [267, 268, 1], [268, 269, 1], [269, 270, 1], [270, 271, 1], [271, 272, 1], [272, 273, 1], [153, 185, 1], [37, 72, 1], [5, 37, 1], [73, 107, 1], [51, 73, 1], [107, 147, 1], [106, 107, 1], [106, 283, 1], [106, 150, 1], [147, 179, 1], [71, 283, 1], [150, 182, 1], [54, 71, 1], [70, 71, 1], [70, 289, 1], [38, 70, 1], [104, 290, 1], [104, 105, 1], [104, 134, 1], [289, 290, 1], [105, 122, 1], [134, 166, 1], [82, 105, 1], [82, 315, 1], [122, 123, 1], [122, 140, 1], [123, 299, 1], [123, 151, 1], [140, 172, 1], [120, 299, 1], [120, 121, 1], [151, 183, 1], [93, 120, 1], [121, 146, 1], [118, 121, 1], [118, 322, 1], [146, 178, 1], [83, 93, 1], [83, 318, 1], [92, 93, 1], [92, 95, 1], [42, 92, 1], [95, 138, 1], [94, 95, 1], [94, 329, 1], [138, 170, 1], [44, 82, 1], [12, 44, 1], [315, 316, 1], [316, 317, 1], [317, 318, 1], [55, 83, 1], [87, 118, 1], [87, 336, 1], [119, 322, 1], [119, 155, 1], [119, 325, 1], [155, 187, 1], [325, 326, 1], [326, 327, 1], [327, 328, 1], [328, 329, 1], [74, 94, 1], [74, 75, 1], [59, 74, 1], [27, 59, 1], [81, 87, 1], [86, 336, 1], [86, 156, 1], [60, 86, 1], [28, 60, 1], [156, 188, 1], [50, 81, 1], [18, 50, 1], [80, 81, 1], [29, 61, 1], [26, 58, 1], [13, 45, 1], [16, 48, 1], [25, 57, 1], [30, 62, 1], [7, 39, 1], [6, 38, 1], [22, 54, 1], [19, 51, 1], [10, 42, 1], [17, 49, 1], [23, 55, 1], [0, 32, 1]]}